dayu/__init__.py
dayu/api.py
dayu/exceptions.py
dayu/utils.py
dayu/cores/__init__.py
dayu/cores/engine.py
dayu/cores/rlock.py
dayu/engines/__init__.py
dayu/engines/mixin.py
dayu/engines/timewindows.py
dayu/engines/uniform.py
dayu_ratelimit-1.2.5.dist-info/LICENSE
dayu_ratelimit-1.2.5.dist-info/METADATA
dayu_ratelimit-1.2.5.dist-info/WHEEL
dayu_ratelimit-1.2.5.dist-info/top_level.txt
dayu_ratelimit-1.2.5.dist-info/RECORD
